graphexec/__init__.py
graphexec/cli.py
graphexec/generate_js_module.py
graphexec/litegraph_model.py
graphexec/litegraph_processor.py
graphexec/model.py
graphexec/node_type.py
graphexec/server.py
graphexec-0.0.1.dist-info/LICENSE
graphexec-0.0.1.dist-info/METADATA
graphexec-0.0.1.dist-info/WHEEL
graphexec-0.0.1.dist-info/entry_points.txt
graphexec-0.0.1.dist-info/top_level.txt
graphexec-0.0.1.dist-info/RECORD
