Metadata-Version: 2.1
Name: graphexec
Version: 0.0.1
Summary: Execute litegraph.js graphs server-side
Home-page: https://github.com/mcejp/graphexec
License: MIT
Keywords: litegraph
Platform: UNKNOWN
Classifier: Development Status :: 3 - Alpha
Classifier: Environment :: Console
Classifier: Environment :: Web Environment
Classifier: Framework :: Flask
Classifier: License :: OSI Approved :: MIT License
Classifier: Programming Language :: Python :: 3
Classifier: Programming Language :: Python :: 3.9
Requires-Python: >=3.9
License-File: LICENSE
Requires-Dist: Jinja2
Requires-Dist: Flask
Requires-Dist: numpy
Requires-Dist: pydantic
Provides-Extra: dev
Requires-Dist: black ; extra == 'dev'
Requires-Dist: mypy ; extra == 'dev'
